powersets/__init__.py
powersets/powerset1.py
powersets-0.0.1.dist-info/METADATA
powersets-0.0.1.dist-info/WHEEL
powersets-0.0.1.dist-info/top_level.txt
powersets-0.0.1.dist-info/RECORD
