Metadata-Version: 2.1
Name: powersets
Version: 0.0.1
Summary: algoritmo powerset
Author: debora
License: UNKNOWN
Platform: UNKNOWN
Requires-Python: >=3.8
